{
  "directed": false,
  "multigraph": false,
  "graph": {},
  "nodes": [
    {
      "pos": [
        64,
        39
      ],
      "id": [
        64,
        39
      ]
    },
    {
      "pos": [
        64,
        79
      ],
      "id": [
        64,
        79
      ]
    },
    {
      "pos": [
        50,
        79
      ],
      "id": [
        50,
        79
      ]
    },
    {
      "pos": [
        50,
        39
      ],
      "id": [
        50,
        39
      ]
    },
    {
      "pos": [
        100,
        0
      ],
      "id": [
        100,
        0
      ]
    },
    {
      "pos": [
        100,
        100
      ],
      "id": [
        100,
        100
      ]
    },
    {
      "pos": [
        0,
        100
      ],
      "id": [
        0,
        100
      ]
    },
    {
      "pos": [
        0,
        0
      ],
      "id": [
        0,
        0
      ]
    }
  ],
  "links": [
    {
      "is_vertical": true,
      "source": [
        64,
        39
      ],
      "target": [
        64,
        79
      ]
    },
    {
      "is_vertical": false,
      "source": [
        64,
        39
      ],
      "target": [
        50,
        39
      ]
    },
    {
      "is_vertical": false,
      "source": [
        64,
        79
      ],
      "target": [
        50,
        79
      ]
    },
    {
      "is_vertical": true,
      "source": [
        50,
        79
      ],
      "target": [
        50,
        39
      ]
    },
    {
      "is_vertical": true,
      "source": [
        100,
        0
      ],
      "target": [
        100,
        100
      ]
    },
    {
      "is_vertical": false,
      "source": [
        100,
        0
      ],
      "target": [
        0,
        0
      ]
    },
    {
      "is_vertical": false,
      "source": [
        100,
        100
      ],
      "target": [
        0,
        100
      ]
    },
    {
      "is_vertical": true,
      "source": [
        0,
        100
      ],
      "target": [
        0,
        0
      ]
    }
  ],
  "half_edge_height_dict": {
    "[[64, 39], [64, 79]]": 16,
    "[[64, 79], [64, 39]]": 26,
    "[[64, 39], [50, 39]]": 26,
    "[[50, 39], [64, 39]]": 16,
    "[[64, 79], [50, 79]]": 16,
    "[[50, 79], [64, 79]]": 26,
    "[[50, 79], [50, 39]]": 16,
    "[[50, 39], [50, 79]]": 26,
    "[[100, 0], [100, 100]]": 26,
    "[[100, 100], [100, 0]]": 0,
    "[[100, 0], [0, 0]]": 0,
    "[[0, 0], [100, 0]]": 26,
    "[[100, 100], [0, 100]]": 26,
    "[[0, 100], [100, 100]]": 0,
    "[[0, 100], [0, 0]]": 26,
    "[[0, 0], [0, 100]]": 0
  },
  "source_and_destination": {
    "source": [
      11,
      79,
      8
    ],
    "destination": [
      77,
      90,
      10
    ]
  }
}