{
  "directed": false,
  "multigraph": false,
  "graph": {},
  "nodes": [
    {
      "pos": [
        57,
        15
      ],
      "id": [
        57,
        15
      ]
    },
    {
      "pos": [
        57,
        36
      ],
      "id": [
        57,
        36
      ]
    },
    {
      "pos": [
        51,
        36
      ],
      "id": [
        51,
        36
      ]
    },
    {
      "pos": [
        51,
        15
      ],
      "id": [
        51,
        15
      ]
    },
    {
      "pos": [
        100,
        0
      ],
      "id": [
        100,
        0
      ]
    },
    {
      "pos": [
        100,
        100
      ],
      "id": [
        100,
        100
      ]
    },
    {
      "pos": [
        0,
        100
      ],
      "id": [
        0,
        100
      ]
    },
    {
      "pos": [
        0,
        0
      ],
      "id": [
        0,
        0
      ]
    }
  ],
  "links": [
    {
      "is_vertical": true,
      "source": [
        57,
        15
      ],
      "target": [
        57,
        36
      ]
    },
    {
      "is_vertical": false,
      "source": [
        57,
        15
      ],
      "target": [
        51,
        15
      ]
    },
    {
      "is_vertical": false,
      "source": [
        57,
        36
      ],
      "target": [
        51,
        36
      ]
    },
    {
      "is_vertical": true,
      "source": [
        51,
        36
      ],
      "target": [
        51,
        15
      ]
    },
    {
      "is_vertical": true,
      "source": [
        100,
        0
      ],
      "target": [
        100,
        100
      ]
    },
    {
      "is_vertical": false,
      "source": [
        100,
        0
      ],
      "target": [
        0,
        0
      ]
    },
    {
      "is_vertical": false,
      "source": [
        100,
        100
      ],
      "target": [
        0,
        100
      ]
    },
    {
      "is_vertical": true,
      "source": [
        0,
        100
      ],
      "target": [
        0,
        0
      ]
    }
  ],
  "half_edge_height_dict": {
    "[[57, 15], [57, 36]]": 38,
    "[[57, 36], [57, 15]]": 91,
    "[[57, 15], [51, 15]]": 91,
    "[[51, 15], [57, 15]]": 38,
    "[[57, 36], [51, 36]]": 38,
    "[[51, 36], [57, 36]]": 91,
    "[[51, 36], [51, 15]]": 38,
    "[[51, 15], [51, 36]]": 91,
    "[[100, 0], [100, 100]]": 91,
    "[[100, 100], [100, 0]]": 0,
    "[[100, 0], [0, 0]]": 0,
    "[[0, 0], [100, 0]]": 91,
    "[[100, 100], [0, 100]]": 91,
    "[[0, 100], [100, 100]]": 0,
    "[[0, 100], [0, 0]]": 91,
    "[[0, 0], [0, 100]]": 0
  },
  "source_and_destination": {
    "source": [
      43,
      9,
      83
    ],
    "destination": [
      78,
      1,
      57
    ]
  }
}