{
  "directed": false,
  "multigraph": false,
  "graph": {},
  "nodes": [
    {
      "pos": [
        57,
        16
      ],
      "id": [
        57,
        16
      ]
    },
    {
      "pos": [
        57,
        31
      ],
      "id": [
        57,
        31
      ]
    },
    {
      "pos": [
        18,
        31
      ],
      "id": [
        18,
        31
      ]
    },
    {
      "pos": [
        18,
        16
      ],
      "id": [
        18,
        16
      ]
    },
    {
      "pos": [
        42,
        77
      ],
      "id": [
        42,
        77
      ]
    },
    {
      "pos": [
        42,
        88
      ],
      "id": [
        42,
        88
      ]
    },
    {
      "pos": [
        33,
        88
      ],
      "id": [
        33,
        88
      ]
    },
    {
      "pos": [
        33,
        77
      ],
      "id": [
        33,
        77
      ]
    },
    {
      "pos": [
        100,
        0
      ],
      "id": [
        100,
        0
      ]
    },
    {
      "pos": [
        100,
        100
      ],
      "id": [
        100,
        100
      ]
    },
    {
      "pos": [
        0,
        100
      ],
      "id": [
        0,
        100
      ]
    },
    {
      "pos": [
        0,
        0
      ],
      "id": [
        0,
        0
      ]
    }
  ],
  "links": [
    {
      "is_vertical": true,
      "source": [
        57,
        16
      ],
      "target": [
        57,
        31
      ]
    },
    {
      "is_vertical": false,
      "source": [
        57,
        16
      ],
      "target": [
        18,
        16
      ]
    },
    {
      "is_vertical": false,
      "source": [
        57,
        31
      ],
      "target": [
        18,
        31
      ]
    },
    {
      "is_vertical": true,
      "source": [
        18,
        31
      ],
      "target": [
        18,
        16
      ]
    },
    {
      "is_vertical": true,
      "source": [
        42,
        77
      ],
      "target": [
        42,
        88
      ]
    },
    {
      "is_vertical": false,
      "source": [
        42,
        77
      ],
      "target": [
        33,
        77
      ]
    },
    {
      "is_vertical": false,
      "source": [
        42,
        88
      ],
      "target": [
        33,
        88
      ]
    },
    {
      "is_vertical": true,
      "source": [
        33,
        88
      ],
      "target": [
        33,
        77
      ]
    },
    {
      "is_vertical": true,
      "source": [
        100,
        0
      ],
      "target": [
        100,
        100
      ]
    },
    {
      "is_vertical": false,
      "source": [
        100,
        0
      ],
      "target": [
        0,
        0
      ]
    },
    {
      "is_vertical": false,
      "source": [
        100,
        100
      ],
      "target": [
        0,
        100
      ]
    },
    {
      "is_vertical": true,
      "source": [
        0,
        100
      ],
      "target": [
        0,
        0
      ]
    }
  ],
  "half_edge_height_dict": {
    "[[57, 16], [57, 31]]": 79,
    "[[57, 31], [57, 16]]": 14,
    "[[57, 16], [18, 16]]": 14,
    "[[18, 16], [57, 16]]": 79,
    "[[57, 31], [18, 31]]": 79,
    "[[18, 31], [57, 31]]": 14,
    "[[18, 31], [18, 16]]": 79,
    "[[18, 16], [18, 31]]": 14,
    "[[42, 77], [42, 88]]": 33,
    "[[42, 88], [42, 77]]": 14,
    "[[42, 77], [33, 77]]": 14,
    "[[33, 77], [42, 77]]": 33,
    "[[42, 88], [33, 88]]": 33,
    "[[33, 88], [42, 88]]": 14,
    "[[33, 88], [33, 77]]": 33,
    "[[33, 77], [33, 88]]": 14,
    "[[100, 0], [100, 100]]": 14,
    "[[100, 100], [100, 0]]": 0,
    "[[100, 0], [0, 0]]": 0,
    "[[0, 0], [100, 0]]": 14,
    "[[100, 100], [0, 100]]": 14,
    "[[0, 100], [100, 100]]": 0,
    "[[0, 100], [0, 0]]": 14,
    "[[0, 0], [0, 100]]": 0
  },
  "source_and_destination": {
    "source": [
      57,
      61,
      7
    ],
    "destination": [
      54,
      21,
      60
    ]
  }
}