{
  "directed": false,
  "multigraph": false,
  "graph": {},
  "nodes": [
    {
      "pos": [
        83,
        42
      ],
      "id": [
        83,
        42
      ]
    },
    {
      "pos": [
        83,
        68
      ],
      "id": [
        83,
        68
      ]
    },
    {
      "pos": [
        47,
        68
      ],
      "id": [
        47,
        68
      ]
    },
    {
      "pos": [
        47,
        42
      ],
      "id": [
        47,
        42
      ]
    },
    {
      "pos": [
        54,
        39
      ],
      "id": [
        54,
        39
      ]
    },
    {
      "pos": [
        54,
        63
      ],
      "id": [
        54,
        63
      ]
    },
    {
      "pos": [
        25,
        63
      ],
      "id": [
        25,
        63
      ]
    },
    {
      "pos": [
        25,
        39
      ],
      "id": [
        25,
        39
      ]
    },
    {
      "pos": [
        100,
        0
      ],
      "id": [
        100,
        0
      ]
    },
    {
      "pos": [
        100,
        100
      ],
      "id": [
        100,
        100
      ]
    },
    {
      "pos": [
        0,
        100
      ],
      "id": [
        0,
        100
      ]
    },
    {
      "pos": [
        0,
        0
      ],
      "id": [
        0,
        0
      ]
    },
    {
      "pos": [
        47,
        63
      ],
      "id": [
        47,
        63
      ]
    },
    {
      "pos": [
        54,
        42
      ],
      "id": [
        54,
        42
      ]
    }
  ],
  "links": [
    {
      "is_vertical": true,
      "source": [
        83,
        42
      ],
      "target": [
        83,
        68
      ]
    },
    {
      "is_vertical": false,
      "source": [
        83,
        42
      ],
      "target": [
        54,
        42
      ]
    },
    {
      "is_vertical": false,
      "source": [
        83,
        68
      ],
      "target": [
        47,
        68
      ]
    },
    {
      "is_vertical": true,
      "source": [
        47,
        68
      ],
      "target": [
        47,
        63
      ]
    },
    {
      "is_vertical": true,
      "source": [
        47,
        42
      ],
      "target": [
        47,
        63
      ]
    },
    {
      "is_vertical": false,
      "source": [
        47,
        42
      ],
      "target": [
        54,
        42
      ]
    },
    {
      "is_vertical": false,
      "source": [
        54,
        39
      ],
      "target": [
        25,
        39
      ]
    },
    {
      "is_vertical": true,
      "source": [
        54,
        39
      ],
      "target": [
        54,
        42
      ]
    },
    {
      "is_vertical": false,
      "source": [
        54,
        63
      ],
      "target": [
        47,
        63
      ]
    },
    {
      "is_vertical": true,
      "source": [
        54,
        63
      ],
      "target": [
        54,
        42
      ]
    },
    {
      "is_vertical": true,
      "source": [
        25,
        63
      ],
      "target": [
        25,
        39
      ]
    },
    {
      "is_vertical": false,
      "source": [
        25,
        63
      ],
      "target": [
        47,
        63
      ]
    },
    {
      "is_vertical": true,
      "source": [
        100,
        0
      ],
      "target": [
        100,
        100
      ]
    },
    {
      "is_vertical": false,
      "source": [
        100,
        0
      ],
      "target": [
        0,
        0
      ]
    },
    {
      "is_vertical": false,
      "source": [
        100,
        100
      ],
      "target": [
        0,
        100
      ]
    },
    {
      "is_vertical": true,
      "source": [
        0,
        100
      ],
      "target": [
        0,
        0
      ]
    }
  ],
  "half_edge_height_dict": {
    "[[83, 42], [83, 68]]": 6,
    "[[83, 68], [83, 42]]": 17,
    "[[83, 42], [54, 42]]": 17,
    "[[54, 42], [83, 42]]": 6,
    "[[83, 68], [47, 68]]": 6,
    "[[47, 68], [83, 68]]": 17,
    "[[47, 68], [47, 63]]": 6,
    "[[47, 63], [47, 68]]": 17,
    "[[47, 42], [47, 63]]": 82,
    "[[47, 63], [47, 42]]": 3,
    "[[47, 42], [54, 42]]": 3,
    "[[54, 42], [47, 42]]": 82,
    "[[54, 39], [25, 39]]": 17,
    "[[25, 39], [54, 39]]": 82,
    "[[54, 39], [54, 42]]": 82,
    "[[54, 42], [54, 39]]": 17,
    "[[54, 63], [47, 63]]": 3,
    "[[47, 63], [54, 63]]": 6,
    "[[54, 63], [54, 42]]": 6,
    "[[54, 42], [54, 63]]": 3,
    "[[25, 63], [25, 39]]": 82,
    "[[25, 39], [25, 63]]": 17,
    "[[25, 63], [47, 63]]": 17,
    "[[47, 63], [25, 63]]": 82,
    "[[100, 0], [100, 100]]": 17,
    "[[100, 100], [100, 0]]": 0,
    "[[100, 0], [0, 0]]": 0,
    "[[0, 0], [100, 0]]": 17,
    "[[100, 100], [0, 100]]": 17,
    "[[0, 100], [100, 100]]": 0,
    "[[0, 100], [0, 0]]": 17,
    "[[0, 0], [0, 100]]": 0
  },
  "source_and_destination": {
    "source": [
      71,
      3,
      1
    ],
    "destination": [
      61,
      74,
      9
    ]
  }
}